Metadata-Version: 2.1
Name: from-ge-to-allure-mapper
Version: 0.0.1.7
Summary: Package for mapping test report format from Great Expectations to Allure
Home-page: https://github.com/provectus/from_ge_to_allure_mapper
Author: Bogdan Volodarskiy
Author-email: hesherus@gmail.com
License: MIT
Download-URL: https://github.com/provectus/from_ge_to_allure_mapper/archive/refs/tags/v_01.7.tar.gz
Keywords: DATA_QA,GREAT_EXPECTATIONS,ALLURE
Platform: UNKNOWN
Classifier: Development Status :: 3 - Alpha
Classifier: Intended Audience :: Developers
Classifier: Topic :: Software Development :: Build Tools
Classifier: License :: OSI Approved :: MIT License
Classifier: Programming Language :: Python :: 3
